IMC_decoder/RTLs/imc_decoder_2jan.v
`include	"opcodes.h"

//	Include definition of the control signals

module imc_decoder (clk,  rst , instruction, CS , WE , OE , ADDR_MEM1 ,ADDR_MEM2  , ADDR_MEM3 , DATA_TO_MEM ,DATA_FROM_MEM  , SAEN , EXECUTE_MIG , EXECUTE_MAGIC ,EXECUTE_IMPLY ,EXECUTE_BITWISE  , exec_logical_bitwise);


parameter INSTRUCTION_SIZE = 32 ; 
parameter DATA_MEM_SIZE = 16 ; 
parameter ADDR_MEM_SIZE = 4; 

input		clk , rst ;
input	[INSTRUCTION_SIZE-1:0]	instruction;


// common output 

output reg 		CS;
output reg 		WE;
output reg 		OE;
output reg 	[DATA_MEM_SIZE-1:0] DATA_TO_MEM	;
input 	        [DATA_MEM_SIZE-1:0] DATA_FROM_MEM	;
output reg 	[ADDR_MEM_SIZE-1:0] ADDR_MEM1	;
output reg 	[ADDR_MEM_SIZE-1:0] ADDR_MEM2	;
output reg 	[ADDR_MEM_SIZE-1:0] ADDR_MEM3	;
output reg 	[DATA_MEM_SIZE-1:0] SAEN	;

// MIG special 

output	EXECUTE_MIG	; 
reg [DATA_MEM_SIZE-1:0]data_from_mem;

// MAGIC special 
output	EXECUTE_MAGIC	;

// IMPLY special 
output	EXECUTE_IMPLY	; 

// 
output	EXECUTE_BITWISE	;

reg exec_mig ; 
reg exec_magic ; 
reg exec_imply ; 
reg exec_bitwise ; 

output reg [1:0] exec_logical_bitwise ; 


wire mem_read ;
wire mem_write ; 


// 
// MIG : 16b - 1b extra
//      [14:13] --> MIG/IMPLY/MAGIC/BITWISE - 2b 
//      [12] --/ Read/Write  - 1b
//      [11-8] -- SAEN decode - 4b
//    [7-4] -- write registers - 4b 
//    [0-3] -- temp regs


// For which IMC operation 
always @(posedge clk   ) begin 

			// Check the instruction op-code
case (instruction[31:30])
		`MAJORITY :	// 
                begin
                     exec_mig = 1 ;
                     exec_magic = 0 ;
                     exec_imply  = 0 ; 
                     exec_bitwise = 0 ;
                    
                        case (instruction[29])

                            
                            1'b0: //Read 
                            begin 
                                CS   = 0 ; // active low 
                                WE   = 1 ; // active low
                                ADDR_MEM1 = instruction[28:25];


                            end 
                            1'b1: //write  
                            begin 
                                CS   = 0 ; // active low 
                                WE   = 0 ; // active low
                                ADDR_MEM1 = instruction[28:25];
                                DATA_TO_MEM = instruction[24:8]; // need to write code for mask pattern 
                                 
                            end 
                        endcase
                end 
                        
                `MAGIC :	// 
                begin
                     exec_mig = 0 ;
                     exec_magic = 1 ;
                     exec_imply  = 0 ; 
                     exec_bitwise = 0 ; 
                end




		`IMPLY :	// The instruction is a xor
                begin
                     exec_mig = 0 ;
                     exec_magic = 0 ;
                     exec_imply  = 1 ; 
                     exec_bitwise = 0 ;

                        case (instruction[29])

                            1'b0 :  //exec
                                begin
                                    ADDR_MEM1 = instruction[28:25]   ;
                                    ADDR_MEM1 = instruction[24:21]; 
                                    CS = 0 ; 
                                    WE = 0;
                                end 

                            1'b1 : //copy 
                                  begin
                                    ADDR_MEM1 = instruction[28:25]   ;
                                    ADDR_MEM1 = instruction[24:21]; 
                                    CS = 0 ; 
                                    WE = 1;
                                end 





                        
                        endcase



                end 



            	`BITWISE:	// The instruction is a xor
                begin
                     exec_mig = 0 ;
                     exec_magic = 0 ;
                     exec_imply  = 0 ; 
                     exec_bitwise = 1 ;
                     exec_logical_bitwise = instruction[1:0];
                     ADDR_MEM1 = instruction[29:26];
                     ADDR_MEM2 = instruction[25:22];
                     ADDR_MEM3 = instruction[21:19];
                     CS = 0 ; 
                     WE = 1 ; 

                end

endcase
end


assign  EXECUTE_MIG = exec_mig ;
assign  EXECUTE_MAGIC = exec_magic ;
assign  EXECUTE_IMPLY = exec_imply ;
assign  EXECUTE_BITWISE = exec_bitwise;


// outputs according to the technique



endmodule

IMC_decoder/RTLs/imc_decoder_tb.v

`timescale 1ns / 1ps



//	Include definition of the control signals

module imc_decoder_tb  ();


parameter INSTRUCTION_SIZE = 32 ; 
parameter DATA_MEM_SIZE = 16 ; 
parameter ADDR_MEM_SIZE = 4; 

reg 		clk , rst ;
reg 	[INSTRUCTION_SIZE-1:0]	instruction;


// common output 

wire  		CS;
wire  		WE;
wire  		OE;
wire  	[DATA_MEM_SIZE-1:0] DATA_TO_MEM	;
reg 	        [DATA_MEM_SIZE-1:0] DATA_FROM_MEM	;
wire 	[ADDR_MEM_SIZE-1:0] ADDR_MEM1	;
wire 	[ADDR_MEM_SIZE-1:0] ADDR_MEM2	;
wire 	[ADDR_MEM_SIZE-1:0] ADDR_MEM3	;
wire 	[DATA_MEM_SIZE-1:0] SAEN	;

// MIG special 

wire	EXECUTE_MIG	; 

// MAGIC special 
wire	EXECUTE_MAGIC	;

// IMPLY special 
wire	EXECUTE_IMPLY	; 

// 
output	EXECUTE_BITWISE	;


wire [1:0] exec_logical_bitwise ; 

imc_decoder	  uut (
.clk(clk),  
.rst(rst) , 
.instruction(instruction) , 
.CS(CS) , 
.WE(WE) , 
.OE(OE) , 
.ADDR_MEM1(ADDR_MEM1) ,
.ADDR_MEM2(ADDR_MEM2)  , 
.ADDR_MEM3(ADDR_MEM3) , 
.DATA_TO_MEM(DATA_TO_MEM) ,
.DATA_FROM_MEM(DATA_FROM_MEM)  , 
.SAEN(SAEN) , 
.EXECUTE_MIG(EXECUTE_MIG) , 
.EXECUTE_MAGIC(EXECUTE_MAGIC) ,
.EXECUTE_IMPLY(EXECUTE_IMPLY) ,
.EXECUTE_BITWISE(EXECUTE_BITWISE)  , 
.exec_logical_bitwise(exec_logical_bitwise)
);



	initial begin
		// Initialize Inputs

		clk = 0 ; 
		rst  = 0 ;
		instruction = 0 ;
		DATA_FROM_MEM= 0	;

	#20 
		rst  = 1 ;
		instruction = 32'b10000011000000000000000000000000; //Majority read 


	#35 

	instruction =         32'b10111000000111100000000000000000; // Majority Write 


	#10 

	instruction =         32'b11111000000111100000000000000000; // bitwise and



	#10 
	 instruction = 32'b00011010100000000000000000000000; //IMPLY exec


	#10 

	 instruction = 32'b00111000000000000000000000000000; // IMPLY copy 


	#100 $finish;

  	  end


// outputs according to the technique


	 always  begin
    #5 clk = !clk;  
	 end
	 
initial  begin
    $dumpfile ("imc_decoder_tb.vcd"); 
    $dumpvars; 
  end 


endmodule

IMC_decoder/RTLs/imc_decoder_tb.vcd
$date
	Mon Dec 27 20:01:12 2021
$end
$version
	Icarus Verilog
$end
$timescale
	1ps
$end
$scope module imc_decoder_tb $end
$var wire 2 ! exec_logical_bitwise [1:0] $end
$var wire 1 " WE $end
$var wire 16 # SAEN [15:0] $end
$var wire 1 $ OE $end
$var wire 1 % EXECUTE_MIG $end
$var wire 1 & EXECUTE_MAGIC $end
$var wire 1 ' EXECUTE_IMPLY $end
$var wire 1 ( EXECUTE_BITWISE $end
$var wire 16 ) DATA_TO_MEM [15:0] $end
$var wire 1 * CS $end
$var wire 4 + ADDR_MEM3 [3:0] $end
$var wire 4 , ADDR_MEM2 [3:0] $end
$var wire 4 - ADDR_MEM1 [3:0] $end
$var reg 16 . DATA_FROM_MEM [15:0] $end
$var reg 1 / clk $end
$var reg 32 0 instruction [31:0] $end
$var reg 1 1 rst $end
$scope module uut $end
$var wire 16 2 DATA_FROM_MEM [15:0] $end
$var wire 1 ( EXECUTE_BITWISE $end
$var wire 1 ' EXECUTE_IMPLY $end
$var wire 1 & EXECUTE_MAGIC $end
$var wire 1 % EXECUTE_MIG $end
$var wire 1 / clk $end
$var wire 32 3 instruction [31:0] $end
$var wire 1 1 rst $end
$var reg 4 4 ADDR_MEM1 [3:0] $end
$var reg 4 5 ADDR_MEM2 [3:0] $end
$var reg 4 6 ADDR_MEM3 [3:0] $end
$var reg 1 * CS $end
$var reg 16 7 DATA_TO_MEM [15:0] $end
$var reg 1 $ OE $end
$var reg 16 8 SAEN [15:0] $end
$var reg 1 " WE $end
$var reg 1 9 exec_bitwise $end
$var reg 1 : exec_imply $end
$var reg 2 ; exec_logical_bitwise [1:0] $end
$var reg 1 < exec_magic $end
$var reg 1 = exec_mig $end
$upscope $end
$upscope $end
$enddefinitions $end
#0
$dumpvars
x=
x<
bx ;
x:
x9
bx 8
bx 7
bx 6
bx 5
bx 4
b0 3
b0 2
01
b0 0
0/
b0 .
bx -
bx ,
bx +
x*
bx )
x(
x'
x&
x%
x$
bx #
x"
bx !
$end
#5000
0"
0*
b0 -
b0 4
0(
09
1'
1:
0&
0<
0%
0=
1/
#10000
0/
#15000
1/
#20000
0/
b10000011000000000000000000000000 0
b10000011000000000000000000000000 3
11
#25000
b1 -
b1 4
1"
0'
0:
1%
1=
1/
#30000
0/
#35000
1/
#40000
0/
#45000
1/
#50000
0/
#55000
b1111000000000 )
b1111000000000 7
b1100 -
b1100 4
0"
1/
b10111000000111100000000000000000 0
b10111000000111100000000000000000 3
#60000
0/
#65000
1"
b11 +
b11 6
b0 ,
b0 5
b1110 -
b1110 4
b0 !
b0 ;
1(
19
0%
0=
1/
b11111000000111100000000000000000 0
b11111000000111100000000000000000 3
#70000
0/
#75000
0"
b100 -
b100 4
0(
09
1'
1:
1/
b11010100000000000000000000000 0
b11010100000000000000000000000 3
#80000
0/
#85000
1"
b0 -
b0 4
1/
b111000000000000000000000000000 0
b111000000000000000000000000000 3
#90000
0/
#95000
b0 -
b0 4
1/
#100000
0/
#105000
b0 -
b0 4
1/
#110000
0/
#115000
b0 -
b0 4
1/
#120000
0/
#125000
b0 -
b0 4
1/
#130000
0/
#135000
b0 -
b0 4
1/
#140000
0/
#145000
b0 -
b0 4
1/
#150000
0/
#155000
b0 -
b0 4
1/
#160000
0/
#165000
b0 -
b0 4
1/
#170000
0/
#175000
b0 -
b0 4
1/
#180000
0/
#185000
b0 -
b0 4
1/
