IMC_decoder/RTLs/top.v



module top ( 
clk, 
rstn, 
enable , 
address_start , 
MAJ_OP_REG); 

input clk , rstn ; 

output reg [4:0]address_start; 
output reg [31:0]MAJ_OP_REG; 

output reg enable;

wire [31:0]data_bus_MIG_mem; 

wire [4:0]address_MIG;

vector_register_file_sram  U_MIG_MEM(
.clk(clk),          // Clock Input
.address(address_MIG),      // Address Input
.data(data_bus_MIG_mem),         // Data bi-directional
.cs(CS),           // Chip Select
.we(WE),           // Write Enable/Read Enable
.oe(OE)            // Output Enable
); 



maj_state_machine_3x8_decoder  U_statemachine(.clk(clk), 
	.in(), 
	.rstn(rstn), 
	.enable(enable) , 
	.address_start(address_start) , 
	.execute_MIG(execute_MIG) ,
        .data_bus_MIG_mem(data_bus_MIG_mem), 	
	.WE(WE) , 
	.CS(CS) , 
	.OE(OE) , 
	.address_MIG(address_MIG) , 
	.MAJ_OP_REG(MAJ_OP_REG)  );



always @ (posedge clk  or  negedge rstn ) begin

if (!rstn) 
begin

	MAJ_OP_REG[31:0] =  0;
        enable = 0 ; 	

end	
else begin 
	MAJ_OP_REG[31] =  1'b0; 
	MAJ_OP_REG[30] =  1'b1; 
	MAJ_OP_REG[29] =  1'b1; 
	MAJ_OP_REG[28] =  1'b0; 
	MAJ_OP_REG[27] =  1'b1; 
	MAJ_OP_REG[26:0] = 0 ;  
	enable = 1;
        address_start = 5'b00011;	
	
	end 
end

endmodule 



module maj_state_machine_3x8_decoder (clk, 
	in, 
	rstn, 
	enable , 
	address_start , 
	execute_MIG ,
        data_bus_MIG_mem, 	
	WE , 
	CS , 
	OE , 
	address_MIG , 
	MAJ_OP_REG  );

input   clk, in, rstn , enable ;
input   [31:0]MAJ_OP_REG; 
input   [4:0] address_start;

inout  [31:0]data_bus_MIG_mem;
reg  [31:0]data_bus_MIG_mem_reg_in ;
reg  [31:0]data_bus_MIG_mem_reg_out ;

wire mem_read; 
wire mem_write; 

assign mem_read = CS && ! WE && OE;
assign mem_write = CS && WE ;


output reg [4:0] address_MIG;
output reg WE , CS , OE , execute_MIG ; 

reg out_reg ;

reg     [2:0]state;
    
parameter S0 = 0, S1 = 1, S2 = 2 , S3 = 3 , S4 = 4 , S5=5 , S6=6;

assign data_bus_MIG_mem = out_reg ? data_bus_MIG_mem_reg_out : 32'bz;



always @ (state) begin
case (state)
S0:
begin
  address_MIG <= 'hz;
  out_reg = 0; 	
	WE = 0;
       	OE = 1;
       	CS = 1;	
	data_bus_MIG_mem_reg_in =0;
end 	


S1: 
begin // Read 
	out_reg = 0; 	
	execute_MIG =1;
	address_MIG = 1 ; 
	WE = 0;
       	OE = 1;
       	CS = 1;	
	//Read from databus 
	
		
end 

S2:
begin // Wait for memory response in next cycle and register input to  data_bus_MIG_mem_reg_in
	data_bus_MIG_mem_reg_in  = data_bus_MIG_mem;

end
	


S3:
begin // Write to memory  
	out_reg = 1; 	
	
	data_bus_MIG_mem_reg_out[31] = MAJ_OP_REG[4]   ; // c 
	data_bus_MIG_mem_reg_out[30] = data_bus_MIG_mem_reg_in[30];   // n11
	data_bus_MIG_mem_reg_out[29] = data_bus_MIG_mem_reg_in[29];   // n12
	data_bus_MIG_mem_reg_out[28] = data_bus_MIG_mem_reg_in[31];   // n8 
	data_bus_MIG_mem_reg_out[27] = MAJ_OP_REG[4]  ; // c 
	data_bus_MIG_mem_reg_out[26] = MAJ_OP_REG[2]  ; // a 
	data_bus_MIG_mem_reg_out[25] = MAJ_OP_REG[2]  ; // a 
	data_bus_MIG_mem_reg_out[24] = data_bus_MIG_mem_reg_in[28] ;   // n14 
	data_bus_MIG_mem_reg_out[23:0] = 0 ; 

	address_MIG = address_MIG + 1; 
	WE = 1; 
       	CS = 1 ; //Write to mem
	OE = 0 ; 

end
	
	


	
S4:
begin //Write memory again  

	
	out_reg = 1; 	


	data_bus_MIG_mem_reg_out[31] = MAJ_OP_REG[4] ;  // c 
	data_bus_MIG_mem_reg_out[30] = data_bus_MIG_mem_reg_in[30] ;  // n11
	data_bus_MIG_mem_reg_out[29] = data_bus_MIG_mem_reg_in[29] ;  // n12
	data_bus_MIG_mem_reg_out[28] = data_bus_MIG_mem_reg_in[31] ;  // n8 
	data_bus_MIG_mem_reg_out[27] = MAJ_OP_REG[4];   // c 
	data_bus_MIG_mem_reg_out[26] = MAJ_OP_REG[2];   // a 
	data_bus_MIG_mem_reg_out[25] = MAJ_OP_REG[2];   // a 
	data_bus_MIG_mem_reg_out[24] = data_bus_MIG_mem_reg_in[28]  ; // n14 
	data_bus_MIG_mem_reg_out[23:0] = 0 ; 

	data_bus_MIG_mem_reg_out = 3; 


	address_MIG = address_MIG + 1; 

	WE = 1 ; 
       	CS = 1 ; //Write to mem
	OE = 0 ; 
end
S5:
begin // Read in next cycle for same address : and check if value matches 
	out_reg = 0; 	
	WE = 0;
       	OE = 1;
       	CS = 1;	
	//Read from databus 
	
	//data_bus_MIG_mem_reg_in  = data_bus_MIG_mem;

	


end


S6:
begin // Wait for one more cycle for data to come back and latch 
	out_reg = 0; 	
	WE = 0;
       	OE = 1;
       	CS = 1;	
	//Read from databus 
	
	data_bus_MIG_mem_reg_in  = data_bus_MIG_mem;

	


end



endcase
end


always @ (posedge clk  or  negedge rstn ) begin

if (!rstn) 
begin
	address_MIG <= 0 ;
	CS <= 0 ;
	execute_MIG  <= 0 ; 
	state <= S0;

end	
	
else if (enable)
	case (state)
	   	S0:
      			state <= S1;
   		S1:
         		state <= S2;
   		S2:
         		state <= S3;

		S3:
         		state <= S4;

		S4:
         		state <= S5;
		S5:
         		state <= S6;


		S6:
         		state <= S0;


endcase
end
endmodule

IMC_decoder/RTLs/memory/vector_register_file.v
// Function    : Synchronous read write RAM 
module vector_register_file_sram (
clk         , // Clock Input
address     , // Address Input
data        , // Data bi-directional
cs          , // Chip Select
we          , // Write Enable/Read Enable
oe            // Output Enable
); 

parameter DATA_WIDTH = 32 ;
parameter ADDR_WIDTH = 5 ;
parameter RAM_DEPTH = 1 << ADDR_WIDTH;

//--------------Input Ports----------------------- 
input                  clk         ;
input [ADDR_WIDTH-1:0] address     ;
input                  cs          ;
input                  we          ;
input                  oe          ; 

//--------------Inout Ports----------------------- 
inout [DATA_WIDTH-1:0]  data       ;

//--------------Internal variables---------------- 
reg [DATA_WIDTH-1:0] data_out ;
reg [DATA_WIDTH-1:0] mem [0:RAM_DEPTH-1];
reg                  oe_r;

//--------------Code Starts Here------------------ 

// Tri-State Buffer control 
// output : When we = 0, oe = 1, cs = 1
assign data = (cs && oe && !we) ? data_out : 32'bz; 

// Memory Write Block 
// Write Operation : When we = 1, cs = 1
always @ (posedge clk)
begin : MEM_WRITE
   if ( cs && we ) begin
       mem[address] = data;
   end
end

// Memory Read Block 
// Read Operation : When we = 0, oe = 1, cs = 1
always @ (posedge clk)
begin : MEM_READ
  if (cs && !we && oe) begin
    data_out = mem[address];
    oe_r = 1;
  end else begin
    oe_r = 0;
  end
end

//initialize memory 
initial $readmemb("data.txt",mem);



endmodule // End of Module ram_sp_sr_sw

IMC_decoder/RTLs/top_tb.v
module top_tb (); 



top uut( 
clk, 
rstn, 
enable , 
address_start , 
MAJ_OP_REG); 


reg clk , rstn ; 
wire enable; 
wire [4:0]address_start; 
wire [31:0]MAJ_OP_REG;

initial begin 


#5 

rstn = 0;
	
clk = 0 ; 
#10 
rstn = 1 ;  

#80 
$finish;


end
	

 always  begin
	#5 clk = !clk;  
 end
	 
initial  begin
    $dumpfile ("top_tb.vcd"); 
    $dumpvars; 
  end 



  endmodule

IMC_decoder/RTLs/top_tb.vcd
$date
	Tue Jan  4 20:18:12 2022
$end
$version
	Icarus Verilog
$end
$timescale
	1s
$end
$scope module top_tb $end
$var wire 1 ! enable $end
$var wire 5 " address_start [4:0] $end
$var wire 32 # MAJ_OP_REG [31:0] $end
$var reg 1 $ clk $end
$var reg 1 % rstn $end
$scope module uut $end
$var wire 1 $ clk $end
$var wire 32 & data_bus_MIG_mem [31:0] $end
$var wire 1 % rstn $end
$var wire 1 ' execute_MIG $end
$var wire 5 ( address_MIG [4:0] $end
$var wire 1 ) WE $end
$var wire 1 * OE $end
$var wire 1 + CS $end
$var reg 32 , MAJ_OP_REG [31:0] $end
$var reg 5 - address_start [4:0] $end
$var reg 1 ! enable $end
$scope module U_MIG_MEM $end
$var wire 1 $ clk $end
$var wire 32 . data [31:0] $end
$var wire 1 ) we $end
$var wire 1 * oe $end
$var wire 1 + cs $end
$var wire 5 / address [4:0] $end
$var reg 32 0 data_out [31:0] $end
$var reg 1 1 oe_r $end
$scope begin MEM_READ $end
$upscope $end
$scope begin MEM_WRITE $end
$upscope $end
$upscope $end
$scope module U_statemachine $end
$var wire 32 2 MAJ_OP_REG [31:0] $end
$var wire 5 3 address_start [4:0] $end
$var wire 1 $ clk $end
$var wire 32 4 data_bus_MIG_mem [31:0] $end
$var wire 1 ! enable $end
$var wire 1 5 in $end
$var wire 1 6 mem_read $end
$var wire 1 7 mem_write $end
$var wire 1 % rstn $end
$var reg 1 + CS $end
$var reg 1 * OE $end
$var reg 1 ) WE $end
$var reg 5 8 address_MIG [4:0] $end
$var reg 32 9 data_bus_MIG_mem_reg_in [31:0] $end
$var reg 32 : data_bus_MIG_mem_reg_out [31:0] $end
$var reg 1 ' execute_MIG $end
$var reg 1 ; out_reg $end
$var reg 3 < state [2:0] $end
$upscope $end
$upscope $end
$upscope $end
$enddefinitions $end
#0
$dumpvars
bx <
x;
bx :
bx 9
bx 8
x7
x6
z5
bx 4
bx 3
bx 2
x1
bx 0
bx /
bx .
bx -
bx ,
x+
x*
x)
bx (
x'
bx &
x%
x$
bx #
bx "
x!
$end
#5
bx &
bx .
bx 4
16
b0 9
1*
0)
0;
07
b0 <
0'
1+
bz (
bz /
bz 8
01
0!
b0 #
b0 ,
b0 2
1$
0%
#10
0$
#15
11
b11 "
b11 -
b11 3
1!
b1101000000000000000000000000000 #
b1101000000000000000000000000000 ,
b1101000000000000000000000000000 2
1$
1%
#20
0$
#25
b1 (
b1 /
b1 8
1'
b1 <
1$
#30
0$
#35
b10 (
b10 /
b10 8
b111111100000000000000000000000 9
b101 :
b10 <
b111111100000000000000000000000 &
b111111100000000000000000000000 .
b111111100000000000000000000000 4
b111111100000000000000000000000 0
1$
#40
0$
#45
06
17
b100001000000000000000000000000 &
b100001000000000000000000000000 .
b100001000000000000000000000000 4
0*
1)
b11 (
b11 /
b11 8
b100001000000000000000000000000 :
1;
b11 <
1$
#50
0$
#55
b11 &
b11 .
b11 4
b100 (
b100 /
b100 8
b11 :
b100 <
01
1$
#60
0$
#65
16
07
b111111100000000000000000000000 &
b111111100000000000000000000000 .
b111111100000000000000000000000 4
1*
0)
0;
b101 <
1$
#70
0$
#75
b11 9
b110 <
b11 &
b11 .
b11 4
11
b11 0
1$
#80
0$
#85
bz (
bz /
bz 8
b0 9
b0 <
1$
#90
0$
#95
b1 (
b1 /
b1 8
b1 <
bx &
bx .
bx 4
bx 0
1$
