RTLs_1409/pwm_90.v
 
module pwm_90(CLK, RST, OUTPUT ); 
 
    parameter PERIOD_WIDTH = 10.0; 
    parameter DUTY_CYCLE = 90.0 ; 
    parameter PULSE_WIDTH = PERIOD_WIDTH*(DUTY_CYCLE/100);  


    parameter BITS = 4; 


 
    input CLK; 
    input RST; 
    output OUTPUT; 
     
    wire CLK; 
    wire RST; 
    wire OUTPUT; 
 
    reg [BITS-1:0] count; 
    reg outtemp; 
 
    always @(posedge CLK or posedge RST) 
    begin 
        if (RST) 
        begin 
            count <= 0; 
            outtemp <= 0; 
        end 
        else 
        begin

            if (count < PULSE_WIDTH) 
            begin 
                outtemp <= 1'b1; 
                count <= count + 1; 
            end 
            else if (count < PERIOD_WIDTH) 
            begin 
                outtemp <= 1'b0; 
                count <= count + 1; 
            end 
            else 
            begin 
                count <= 1; 
                outtemp <= 1'b1; 
            end 
        end 
    end 
     
    assign OUTPUT = outtemp; 
 
endmodule

RTLs_1409/pwm_70.v
 
module pwm_70(CLK, RST, OUTPUT ); 
 
    parameter PERIOD_WIDTH = 10.0; 
    parameter DUTY_CYCLE = 70.0 ; 
    parameter PULSE_WIDTH = PERIOD_WIDTH*(DUTY_CYCLE/100);  


    parameter BITS = 4; 


 
    input CLK; 
    input RST; 
    output OUTPUT; 
     
    wire CLK; 
    wire RST; 
    wire OUTPUT; 
 
    reg [BITS-1:0] count; 
    reg outtemp; 
 
    always @(posedge CLK or posedge RST) 
    begin 
        if (RST) 
        begin 
            count <= 0; 
            outtemp <= 0; 
        end 
        else 
        begin

            if (count < PULSE_WIDTH) 
            begin 
                outtemp <= 1'b1; 
                count <= count + 1; 
            end 
            else if (count < PERIOD_WIDTH) 
            begin 
                outtemp <= 1'b0; 
                count <= count + 1; 
            end 
            else 
            begin 
                count <= 1; 
                outtemp <= 1'b1; 
            end 
        end 
    end 
     
    assign OUTPUT = outtemp; 
 
endmodule

RTLs_1409/pwm_50.v
 
module pwm_50(CLK, RST, OUTPUT ); 
 
    parameter PERIOD_WIDTH = 10.0; 
    parameter DUTY_CYCLE = 50.0 ; 
    parameter PULSE_WIDTH = PERIOD_WIDTH*(DUTY_CYCLE/100);  


    parameter BITS = 4; 


 
    input CLK; 
    input RST; 
    output OUTPUT; 
     
    wire CLK; 
    wire RST; 
    wire OUTPUT; 
 
    reg [BITS-1:0] count; 
    reg outtemp; 
 
    always @(posedge CLK or posedge RST) 
    begin 
        if (RST) 
        begin 
            count <= 0; 
            outtemp <= 0; 
        end 
        else 
        begin

            if (count < PULSE_WIDTH) 
            begin 
                outtemp <= 1'b1; 
                count <= count + 1; 
            end 
            else if (count < PERIOD_WIDTH) 
            begin 
                outtemp <= 1'b0; 
                count <= count + 1; 
            end 
            else 
            begin 
                count <= 1; 
                outtemp <= 1'b1; 
            end 
        end 
    end 
     
    assign OUTPUT = outtemp; 
 
endmodule

RTLs_1409/pwm_30.v
 
module pwm_30(CLK, RST, OUTPUT ); 
 
    parameter PERIOD_WIDTH = 10.0; 
    parameter DUTY_CYCLE = 30.0 ; 
    parameter PULSE_WIDTH = PERIOD_WIDTH*(DUTY_CYCLE/100);  


    parameter BITS = 4; 


 
    input CLK; 
    input RST; 
    output OUTPUT; 
     
    wire CLK; 
    wire RST; 
    wire OUTPUT; 
 
    reg [BITS-1:0] count; 
    reg outtemp; 
 
    always @(posedge CLK or posedge RST) 
    begin 
        if (RST) 
        begin 
            count <= 0; 
            outtemp <= 0; 
        end 
        else 
        begin

            if (count < PULSE_WIDTH) 
            begin 
                outtemp <= 1'b1; 
                count <= count + 1; 
            end 
            else if (count < PERIOD_WIDTH) 
            begin 
                outtemp <= 1'b0; 
                count <= count + 1; 
            end 
            else 
            begin 
                count <= 1; 
                outtemp <= 1'b1; 
            end 
        end 
    end 
     
    assign OUTPUT = outtemp; 
 
endmodule

RTLs_1409/mux4x1.v
module mux_4x1 ( input  a,                 
                         input  b,           
                         input  c,           
                         input  d,           
                         input [1:0] sel,    
                         output  out);       

   // When sel[1] is 0, (sel[0]? b:a) is selected and when sel[1] is 1, (sel[0] ? d:c) is taken
   // When sel[0] is 0, a is sent to output, else b and when sel[0] is 0, c is sent to output, else d
   assign out = sel[1] ? (sel[0] ? d : c) : (sel[0] ? b : a);

endmodule

RTLs_1409/pwm.v
 
module pwm(CLK, RST, OUTPUT , SELECT ); 

input CLK , RST ;
input [1:0]SELECT;
output OUTPUT;


mux_4x1  U_sel_pwm( .a(output_pwm_30) ,  .b(output_pwm_50) ,  .c(output_pwm_70) ,  .d(output_pwm_90) ,  .sel(SELECT) ,  .out(OUTPUT) );    


pwm_30  U_pwm_30 (.CLK(CLK), .RST(RST), .OUTPUT(output_pwm_30) ); 
pwm_50  U_pwm_50 (.CLK(CLK), .RST(RST), .OUTPUT(output_pwm_50) ); 
pwm_70  U_pwm_70 (.CLK(CLK), .RST(RST), .OUTPUT(output_pwm_70) ); 
pwm_90  U_pwm_90 (.CLK(CLK), .RST(RST), .OUTPUT(output_pwm_90) ); 







 
endmodule

RTLs_1409/pwm_tb_2809.v
`timescale 1ns / 1ps


module pwm_tb; 
     
    reg CLK; 
    reg RST; 
reg [1:0]SELECT;
    wire OUTPUT; 
    integer clkcount; 
   
    pwm pwm_test1(.CLK(CLK), .RST(RST), .OUTPUT(OUTPUT) , .SELECT(SELECT)); 
   
    initial 
    begin 
        clkcount = 0; 
        $timeformat(-9, 2, "ns", 16); 
        $monitor("CLK = %b , RST = %b , OUTPUT = %b , clkcount = %d , time = %t \n", CLK, RST, OUTPUT, clkcount, $realtime); 
        #101; 
        RST = 0; 
        #101; 
        RST = 1; 
        #101; 
        RST = 0;

	SELECT = 0 ; 

	#100 ; 
	SELECT = 1 ; 
	
 	#100 ; 
	SELECT = 2 ; 

	#100 ; 
	SELECT = 3 ; 

        #1000; 
        $finish; 
    end 
   
    always 
    begin 
        CLK = 1; 
        #5; 
        CLK = 0; 
        #5; 
        clkcount = clkcount + 1; 
    end 
  

initial  begin
    $dumpfile ("pwm_tb.vcd"); 
    $dumpvars; 
  end 


 
   
endmodule

RTLs_1409/pwm_tb.vcd
$date
	Wed Sep 28 19:48:48 2022
$end
$version
	Icarus Verilog
$end
$timescale
	1ps
$end
$scope module pwm_tb $end
$var wire 1 ! OUTPUT $end
$var reg 1 " CLK $end
$var reg 1 # RST $end
$var reg 2 $ SELECT [1:0] $end
$var integer 32 % clkcount [31:0] $end
$scope module pwm_test1 $end
$var wire 1 " CLK $end
$var wire 1 # RST $end
$var wire 2 & SELECT [1:0] $end
$var wire 1 ' output_pwm_90 $end
$var wire 1 ( output_pwm_70 $end
$var wire 1 ) output_pwm_50 $end
$var wire 1 * output_pwm_30 $end
$var wire 1 ! OUTPUT $end
$scope module U_pwm_30 $end
$var wire 1 " CLK $end
$var wire 1 # RST $end
$var wire 1 * OUTPUT $end
$var reg 4 + count [3:0] $end
$var reg 1 * outtemp $end
$upscope $end
$scope module U_pwm_50 $end
$var wire 1 " CLK $end
$var wire 1 # RST $end
$var wire 1 ) OUTPUT $end
$var reg 4 , count [3:0] $end
$var reg 1 ) outtemp $end
$upscope $end
$scope module U_pwm_70 $end
$var wire 1 " CLK $end
$var wire 1 # RST $end
$var wire 1 ( OUTPUT $end
$var reg 4 - count [3:0] $end
$var reg 1 ( outtemp $end
$upscope $end
$scope module U_pwm_90 $end
$var wire 1 " CLK $end
$var wire 1 # RST $end
$var wire 1 ' OUTPUT $end
$var reg 4 . count [3:0] $end
$var reg 1 ' outtemp $end
$upscope $end
$scope module U_sel_pwm $end
$var wire 1 * a $end
$var wire 1 ) b $end
$var wire 1 ( c $end
$var wire 1 ' d $end
$var wire 2 / sel [1:0] $end
$var wire 1 ! out $end
$upscope $end
$upscope $end
$upscope $end
$enddefinitions $end
#0
$dumpvars
bx /
bx .
bx -
bx ,
bx +
1*
1)
1(
1'
bx &
b0 %
bx $
x#
1"
1!
$end
#5000
0"
#10000
1"
b1 %
#15000
0"
#20000
1"
b10 %
#25000
0"
#30000
1"
b11 %
#35000
0"
#40000
1"
b100 %
#45000
0"
#50000
1"
b101 %
#55000
0"
#60000
1"
b110 %
#65000
0"
#70000
1"
b111 %
#75000
0"
#80000
1"
b1000 %
#85000
0"
#90000
1"
b1001 %
#95000
0"
#100000
1"
b1010 %
#101000
0#
#105000
0"
#110000
1"
b1011 %
#115000
0"
#120000
1"
b1100 %
#125000
0"
#130000
1"
b1101 %
#135000
0"
#140000
1"
b1110 %
#145000
0"
#150000
1"
b1111 %
#155000
0"
#160000
1"
b10000 %
#165000
0"
#170000
1"
b10001 %
#175000
0"
#180000
1"
b10010 %
#185000
0"
#190000
1"
b10011 %
#195000
0"
#200000
1"
b10100 %
#202000
0!
0'
b0 .
0(
b0 -
0)
b0 ,
0*
b0 +
1#
#205000
0"
#210000
1"
b10101 %
#215000
0"
#220000
1"
b10110 %
#225000
0"
#230000
1"
b10111 %
#235000
0"
#240000
1"
b11000 %
#245000
0"
#250000
1"
b11001 %
#255000
0"
#260000
1"
b11010 %
#265000
0"
#270000
1"
b11011 %
#275000
0"
#280000
1"
b11100 %
#285000
0"
#290000
1"
b11101 %
#295000
0"
#300000
1"
b11110 %
#303000
b0 $
b0 &
b0 /
0#
#305000
0"
#310000
1!
b1 +
1*
b1 ,
1)
b1 -
1(
b1 .
1'
1"
b11111 %
#315000
0"
#320000
b10 .
b10 -
b10 ,
b10 +
1"
b100000 %
#325000
0"
#330000
b11 +
b11 ,
b11 -
b11 .
1"
b100001 %
#335000
0"
#340000
0!
b100 .
b100 -
b100 ,
b100 +
0*
1"
b100010 %
#345000
0"
#350000
b101 +
b101 ,
b101 -
b101 .
1"
b100011 %
#355000
0"
#360000
b110 .
b110 -
b110 ,
0)
b110 +
1"
b100100 %
#365000
0"
#370000
b111 +
b111 ,
b111 -
b111 .
1"
b100101 %
#375000
0"
#380000
b1000 .
b1000 -
0(
b1000 ,
b1000 +
1"
b100110 %
#385000
0"
#390000
b1001 +
b1001 ,
b1001 -
b1001 .
1"
b100111 %
#395000
0"
#400000
b1010 .
0'
b1010 -
b1010 ,
b1010 +
1"
b101000 %
#403000
b1 $
b1 &
b1 /
#405000
0"
#410000
1!
1*
b1 +
1)
b1 ,
1(
b1 -
1'
b1 .
1"
b101001 %
#415000
0"
#420000
b10 .
b10 -
b10 ,
b10 +
1"
b101010 %
#425000
0"
#430000
b11 +
b11 ,
b11 -
b11 .
1"
b101011 %
#435000
0"
#440000
b100 .
b100 -
b100 ,
b100 +
0*
1"
b101100 %
#445000
0"
#450000
b101 +
b101 ,
b101 -
b101 .
1"
b101101 %
#455000
0"
#460000
0!
b110 .
b110 -
b110 ,
0)
b110 +
1"
b101110 %
#465000
0"
#470000
b111 +
b111 ,
b111 -
b111 .
1"
b101111 %
#475000
0"
#480000
b1000 .
b1000 -
0(
b1000 ,
b1000 +
1"
b110000 %
#485000
0"
#490000
b1001 +
b1001 ,
b1001 -
b1001 .
1"
b110001 %
#495000
0"
#500000
b1010 .
0'
b1010 -
b1010 ,
b1010 +
1"
b110010 %
#503000
b10 $
b10 &
b10 /
#505000
0"
#510000
1!
1*
b1 +
1)
b1 ,
1(
b1 -
1'
b1 .
1"
b110011 %
#515000
0"
#520000
b10 .
b10 -
b10 ,
b10 +
1"
b110100 %
#525000
0"
#530000
b11 +
b11 ,
b11 -
b11 .
1"
b110101 %
#535000
0"
#540000
b100 .
b100 -
b100 ,
b100 +
0*
1"
b110110 %
#545000
0"
#550000
b101 +
b101 ,
b101 -
b101 .
1"
b110111 %
#555000
0"
#560000
b110 .
b110 -
b110 ,
0)
b110 +
1"
b111000 %
#565000
0"
#570000
b111 +
b111 ,
b111 -
b111 .
1"
b111001 %
#575000
0"
#580000
0!
b1000 .
b1000 -
0(
b1000 ,
b1000 +
1"
b111010 %
#585000
0"
#590000
b1001 +
b1001 ,
b1001 -
b1001 .
1"
b111011 %
#595000
0"
#600000
b1010 .
0'
b1010 -
b1010 ,
b1010 +
1"
b111100 %
#603000
b11 $
b11 &
b11 /
#605000
0"
#610000
1!
1*
b1 +
1)
b1 ,
1(
b1 -
1'
b1 .
1"
b111101 %
#615000
0"
#620000
b10 .
b10 -
b10 ,
b10 +
1"
b111110 %
#625000
0"
#630000
b11 +
b11 ,
b11 -
b11 .
1"
b111111 %
#635000
0"
#640000
b100 .
b100 -
b100 ,
b100 +
0*
1"
b1000000 %
#645000
0"
#650000
b101 +
b101 ,
b101 -
b101 .
1"
b1000001 %
#655000
0"
#660000
b110 .
b110 -
b110 ,
0)
b110 +
1"
b1000010 %
#665000
0"
#670000
b111 +
b111 ,
b111 -
b111 .
1"
b1000011 %
#675000
0"
#680000
b1000 .
b1000 -
0(
b1000 ,
b1000 +
1"
b1000100 %
#685000
0"
#690000
b1001 +
b1001 ,
b1001 -
b1001 .
1"
b1000101 %
#695000
0"
#700000
0!
b1010 .
0'
b1010 -
b1010 ,
b1010 +
1"
b1000110 %
#705000
0"
#710000
1!
1*
b1 +
1)
b1 ,
1(
b1 -
1'
b1 .
1"
b1000111 %
#715000
0"
#720000
b10 .
b10 -
b10 ,
b10 +
1"
b1001000 %
#725000
0"
#730000
b11 +
b11 ,
b11 -
b11 .
1"
b1001001 %
#735000
0"
#740000
b100 .
b100 -
b100 ,
b100 +
0*
1"
b1001010 %
#745000
0"
#750000
b101 +
b101 ,
b101 -
b101 .
1"
b1001011 %
#755000
0"
#760000
b110 .
b110 -
b110 ,
0)
b110 +
1"
b1001100 %
#765000
0"
#770000
b111 +
b111 ,
b111 -
b111 .
1"
b1001101 %
#775000
0"
#780000
b1000 .
b1000 -
0(
b1000 ,
b1000 +
1"
b1001110 %
#785000
0"
#790000
b1001 +
b1001 ,
b1001 -
b1001 .
1"
b1001111 %
#795000
0"
#800000
0!
b1010 .
0'
b1010 -
b1010 ,
b1010 +
1"
b1010000 %
#805000
0"
#810000
1!
1*
b1 +
1)
b1 ,
1(
b1 -
1'
b1 .
1"
b1010001 %
#815000
0"
#820000
b10 .
b10 -
b10 ,
b10 +
1"
b1010010 %
#825000
0"
#830000
b11 +
b11 ,
b11 -
b11 .
1"
b1010011 %
#835000
0"
#840000
b100 .
b100 -
b100 ,
b100 +
0*
1"
b1010100 %
#845000
0"
#850000
b101 +
b101 ,
b101 -
b101 .
1"
b1010101 %
#855000
0"
#860000
b110 .
b110 -
b110 ,
0)
b110 +
1"
b1010110 %
#865000
0"
#870000
b111 +
b111 ,
b111 -
b111 .
1"
b1010111 %
#875000
0"
#880000
b1000 .
b1000 -
0(
b1000 ,
b1000 +
1"
b1011000 %
#885000
0"
#890000
b1001 +
b1001 ,
b1001 -
b1001 .
1"
b1011001 %
#895000
0"
#900000
0!
b1010 .
0'
b1010 -
b1010 ,
b1010 +
1"
b1011010 %
#905000
0"
#910000
1!
1*
b1 +
1)
b1 ,
1(
b1 -
1'
b1 .
1"
b1011011 %
#915000
0"
#920000
b10 .
b10 -
b10 ,
b10 +
1"
b1011100 %
#925000
0"
#930000
b11 +
b11 ,
b11 -
b11 .
1"
b1011101 %
#935000
0"
#940000
b100 .
b100 -
b100 ,
b100 +
0*
1"
b1011110 %
#945000
0"
#950000
b101 +
b101 ,
b101 -
b101 .
1"
b1011111 %
#955000
0"
#960000
b110 .
b110 -
b110 ,
0)
b110 +
1"
b1100000 %
#965000
0"
#970000
b111 +
b111 ,
b111 -
b111 .
1"
b1100001 %
#975000
0"
#980000
b1000 .
b1000 -
0(
b1000 ,
b1000 +
1"
b1100010 %
#985000
0"
#990000
b1001 +
b1001 ,
b1001 -
b1001 .
1"
b1100011 %
#995000
0"
#1000000
0!
b1010 .
0'
b1010 -
b1010 ,
b1010 +
1"
b1100100 %
#1005000
0"
#1010000
1!
1*
b1 +
1)
b1 ,
1(
b1 -
1'
b1 .
1"
b1100101 %
#1015000
0"
#1020000
b10 .
b10 -
b10 ,
b10 +
1"
b1100110 %
#1025000
0"
#1030000
b11 +
b11 ,
b11 -
b11 .
1"
b1100111 %
#1035000
0"
#1040000
b100 .
b100 -
b100 ,
b100 +
0*
1"
b1101000 %
#1045000
0"
#1050000
b101 +
b101 ,
b101 -
b101 .
1"
b1101001 %
#1055000
0"
#1060000
b110 .
b110 -
b110 ,
0)
b110 +
1"
b1101010 %
#1065000
0"
#1070000
b111 +
b111 ,
b111 -
b111 .
1"
b1101011 %
#1075000
0"
#1080000
b1000 .
b1000 -
0(
b1000 ,
b1000 +
1"
b1101100 %
#1085000
0"
#1090000
b1001 +
b1001 ,
b1001 -
b1001 .
1"
b1101101 %
#1095000
0"
#1100000
0!
b1010 .
0'
b1010 -
b1010 ,
b1010 +
1"
b1101110 %
#1105000
0"
#1110000
1!
1*
b1 +
1)
b1 ,
1(
b1 -
1'
b1 .
1"
b1101111 %
#1115000
0"
#1120000
b10 .
b10 -
b10 ,
b10 +
1"
b1110000 %
#1125000
0"
#1130000
b11 +
b11 ,
b11 -
b11 .
1"
b1110001 %
#1135000
0"
#1140000
b100 .
b100 -
b100 ,
b100 +
0*
1"
b1110010 %
#1145000
0"
#1150000
b101 +
b101 ,
b101 -
b101 .
1"
b1110011 %
#1155000
0"
#1160000
b110 .
b110 -
b110 ,
0)
b110 +
1"
b1110100 %
#1165000
0"
#1170000
b111 +
b111 ,
b111 -
b111 .
1"
b1110101 %
#1175000
0"
#1180000
b1000 .
b1000 -
0(
b1000 ,
b1000 +
1"
b1110110 %
#1185000
0"
#1190000
b1001 +
b1001 ,
b1001 -
b1001 .
1"
b1110111 %
#1195000
0"
#1200000
0!
b1010 .
0'
b1010 -
b1010 ,
b1010 +
1"
b1111000 %
#1205000
0"
#1210000
1!
1*
b1 +
1)
b1 ,
1(
b1 -
1'
b1 .
1"
b1111001 %
#1215000
0"
#1220000
b10 .
b10 -
b10 ,
b10 +
1"
b1111010 %
#1225000
0"
#1230000
b11 +
b11 ,
b11 -
b11 .
1"
b1111011 %
#1235000
0"
#1240000
b100 .
b100 -
b100 ,
b100 +
0*
1"
b1111100 %
#1245000
0"
#1250000
b101 +
b101 ,
b101 -
b101 .
1"
b1111101 %
#1255000
0"
#1260000
b110 .
b110 -
b110 ,
0)
b110 +
1"
b1111110 %
#1265000
0"
#1270000
b111 +
b111 ,
b111 -
b111 .
1"
b1111111 %
#1275000
0"
#1280000
b1000 .
b1000 -
0(
b1000 ,
b1000 +
1"
b10000000 %
#1285000
0"
#1290000
b1001 +
b1001 ,
b1001 -
b1001 .
1"
b10000001 %
#1295000
0"
#1300000
0!
b1010 .
0'
b1010 -
b1010 ,
b1010 +
1"
b10000010 %
#1305000
0"
#1310000
1!
1*
b1 +
1)
b1 ,
1(
b1 -
1'
b1 .
1"
b10000011 %
#1315000
0"
#1320000
b10 .
b10 -
b10 ,
b10 +
1"
b10000100 %
#1325000
0"
#1330000
b11 +
b11 ,
b11 -
b11 .
1"
b10000101 %
#1335000
0"
#1340000
b100 .
b100 -
b100 ,
b100 +
0*
1"
b10000110 %
#1345000
0"
#1350000
b101 +
b101 ,
b101 -
b101 .
1"
b10000111 %
#1355000
0"
#1360000
b110 .
b110 -
b110 ,
0)
b110 +
1"
b10001000 %
#1365000
0"
#1370000
b111 +
b111 ,
b111 -
b111 .
1"
b10001001 %
#1375000
0"
#1380000
b1000 .
b1000 -
0(
b1000 ,
b1000 +
1"
b10001010 %
#1385000
0"
#1390000
b1001 +
b1001 ,
b1001 -
b1001 .
1"
b10001011 %
#1395000
0"
#1400000
0!
b1010 .
0'
b1010 -
b1010 ,
b1010 +
1"
b10001100 %
#1405000
0"
#1410000
1!
1*
b1 +
1)
b1 ,
1(
b1 -
1'
b1 .
1"
b10001101 %
#1415000
0"
#1420000
b10 .
b10 -
b10 ,
b10 +
1"
b10001110 %
#1425000
0"
#1430000
b11 +
b11 ,
b11 -
b11 .
1"
b10001111 %
#1435000
0"
#1440000
b100 .
b100 -
b100 ,
b100 +
0*
1"
b10010000 %
#1445000
0"
#1450000
b101 +
b101 ,
b101 -
b101 .
1"
b10010001 %
#1455000
0"
#1460000
b110 .
b110 -
b110 ,
0)
b110 +
1"
b10010010 %
#1465000
0"
#1470000
b111 +
b111 ,
b111 -
b111 .
1"
b10010011 %
#1475000
0"
#1480000
b1000 .
b1000 -
0(
b1000 ,
b1000 +
1"
b10010100 %
#1485000
0"
#1490000
b1001 +
b1001 ,
b1001 -
b1001 .
1"
b10010101 %
#1495000
0"
#1500000
0!
b1010 .
0'
b1010 -
b1010 ,
b1010 +
1"
b10010110 %
#1505000
0"
#1510000
1!
1*
b1 +
1)
b1 ,
1(
b1 -
1'
b1 .
1"
b10010111 %
#1515000
0"
#1520000
b10 .
b10 -
b10 ,
b10 +
1"
b10011000 %
#1525000
0"
#1530000
b11 +
b11 ,
b11 -
b11 .
1"
b10011001 %
#1535000
0"
#1540000
b100 .
b100 -
b100 ,
b100 +
0*
1"
b10011010 %
#1545000
0"
#1550000
b101 +
b101 ,
b101 -
b101 .
1"
b10011011 %
#1555000
0"
#1560000
b110 .
b110 -
b110 ,
0)
b110 +
1"
b10011100 %
#1565000
0"
#1570000
b111 +
b111 ,
b111 -
b111 .
1"
b10011101 %
#1575000
0"
#1580000
b1000 .
b1000 -
0(
b1000 ,
b1000 +
1"
b10011110 %
#1585000
0"
#1590000
b1001 +
b1001 ,
b1001 -
b1001 .
1"
b10011111 %
#1595000
0"
#1600000
0!
b1010 .
0'
b1010 -
b1010 ,
b1010 +
1"
b10100000 %
