RTLs_1409/ram_dp_ar_aw.v
// Design Name : ram_dp_ar_aw
// File Name   : ram_dp_ar_aw.v
// Function    : Asynchronous read write RAM
//-----------------------------------------------------
module ram_dp_ar_aw (
address_0 , // address_0 Input
data_0    , // data_0 bi-directional
cs_0      , // Chip Select
we_0      , // Write Enable/Read Enable
oe_0      , // Output Enable
address_1 , // address_1 Input
data_1    , // data_1 bi-directional
cs_1      , // Chip Select
we_1      , // Write Enable/Read Enable
oe_1        // Output Enable
); 

parameter DATA_WIDTH = 8 ;
parameter ADDR_WIDTH = 8 ;
parameter RAM_DEPTH = 1 << ADDR_WIDTH;

//--------------Input Ports----------------------- 
input [ADDR_WIDTH-1:0] address_0 ;
input cs_0 ;
input we_0 ;
input oe_0 ; 
input [ADDR_WIDTH-1:0] address_1 ;
input cs_1 ;
input we_1 ;
input oe_1 ; 

//--------------Inout Ports----------------------- 
input [DATA_WIDTH-1:0] data_0 ; 
output [DATA_WIDTH-1:0] data_1 ;

//--------------Internal variables---------------- 
reg [DATA_WIDTH-1:0] data_0_out ; 
reg [DATA_WIDTH-1:0] data_1_out ;
reg [DATA_WIDTH-1:0] mem [0:RAM_DEPTH-1];

//--------------Code Starts Here------------------ 
// Memory Write Block 
// Write Operation : When we_0 = 1, cs_0 = 1
always @ (address_0 or cs_0 or we_0 or data_0
or address_1 or cs_1 or we_1 or data_1)
begin : MEM_WRITE
  if ( cs_0 && we_0 ) begin
     mem[address_0] <= data_0;
  end else if  (cs_1 && we_1) begin
     mem[address_1] <= data_1;
  end
end

// Tri-State Buffer control 
// output : When we_0 = 0, oe_0 = 1, cs_0 = 1
//assign data_0 = (cs_0 && oe_0 && !we_0) ? data_0_out : 8'bz; 

// Memory Read Block 
// Read Operation : When we_0 = 0, oe_0 = 1, cs_0 = 1
always @ (address_0 or cs_0 or we_1 or oe_0)
begin : MEM_READ_0
  if (cs_0 && !we_0 && oe_0) begin
    data_0_out <= mem[address_0]; 
  end else begin
    data_0_out <= 0; 
  end
end 

//Second Port of RAM
// Tri-State Buffer control 
// output : When we_0 = 0, oe_0 = 1, cs_0 = 1
assign data_1 = (cs_1 && oe_1 && !we_1) ? data_1_out : 8'bz; 
// Memory Read Block 1 
// Read Operation : When we_1 = 0, oe_1 = 1, cs_1 = 1
always @ (address_1 or cs_1 or we_1 or oe_1)
begin : MEM_READ_1
  if (cs_1 && !we_1 && oe_1) begin
    data_1_out <= mem[address_1]; 
  end else begin
    data_1_out <= 0; 
  end
end


//initialize memory 
initial $readmemb("data_if.txt",mem);



endmodule // End of Module ram_dp_ar_aw

RTLs_1409/sync_fifo_16x16.v
//-----------------------------------------------------
// Design Name : syn_fifo
// File Name   : syn_fifo.v
// Function    : Synchronous (single clock) FIFO
//-----------------------------------------------------
module sync_fifo_16x16 (
clk      , // Clock input
rst      , // Active high reset
wr_cs    , // Write chip select
rd_cs    , // Read chipe select
data_in  , // Data input
rd_en    , // Read enable
wr_en    , // Write Enable
data_out , // Data Output
empty    , // FIFO empty
full ,      // FIFO full
address_to_write,
address_to_read
);    
 
// FIFO constants
parameter DATA_WIDTH = 16;
parameter ADDR_WIDTH = 4;
parameter RAM_DEPTH = 16;
// Port Declarations
input clk ;
input rst ;
input wr_cs ;
input rd_cs ;
input rd_en ;
input wr_en ;
input [DATA_WIDTH-1:0] data_in ;
output full ;
output empty ;
output [DATA_WIDTH-1:0] data_out ;

input [ADDR_WIDTH-1:0] address_to_write ;
input [ADDR_WIDTH-1:0] address_to_read;
//-----------Internal variables-------------------
reg [ADDR_WIDTH-1:0] wr_pointer;
reg [ADDR_WIDTH-1:0] rd_pointer;
reg [ADDR_WIDTH :0] status_cnt;
reg [DATA_WIDTH-1:0] data_out ;
wire [DATA_WIDTH-1:0] data_ram ;

//-----------Variable assignments---------------
assign full = (status_cnt == (RAM_DEPTH-1));
assign empty = (status_cnt == 0);

//-----------Code Start---------------------------
always @ (posedge clk or negedge rst)
begin : WRITE_POINTER
  if (!rst) begin
    wr_pointer <= 0;
  end else if (wr_cs && wr_en ) begin
    wr_pointer <= address_to_write ;
  end
end

always @ (posedge clk or negedge rst)
begin : READ_POINTER
  if (!rst) begin
    rd_pointer <= 0;
  end else if (rd_cs && rd_en ) begin
    rd_pointer <= address_to_read ;
  end
end

always  @ (posedge clk or negedge rst)
begin : READ_DATA
  if (!rst) begin
    data_out <= 0;
  end else if (rd_cs && rd_en ) begin
    data_out <= data_ram;
  end
end

always @ (posedge clk or negedge rst)
begin : STATUS_COUNTER
  if (!rst) begin
    status_cnt <= 0;
  // Read but no write.
  end else if ((rd_cs && rd_en) && !(wr_cs && wr_en) 
                && (status_cnt != 0)) begin
    status_cnt <= status_cnt - 1;
  // Write but no read.
  end else if ((wr_cs && wr_en) && !(rd_cs && rd_en) 
               && (status_cnt != RAM_DEPTH)) begin
    status_cnt <= status_cnt + 1;
  end
end 
   
ram_dp_ar_aw #(DATA_WIDTH,ADDR_WIDTH)DP_RAM_IM (
.address_0 (wr_pointer) , // address_0 input 
.data_0    (data_in)    , // data_0 bi-directional
.cs_0      (wr_cs)      , // chip select
.we_0      (wr_en)      , // write enable
.oe_0      (1'b0)       , // output enable
.address_1 (rd_pointer) , // address_q input
.data_1    (data_ram)   , // data_1 bi-directional
.cs_1      (rd_cs)      , // chip select
.we_1      (1'b0)       , // Read enable
.oe_1      (rd_en)        // output enable
);     



endmodule

RTLs_1409/sync_fifo_16x16_tb.v
`timescale 1ns / 1ps
module sync_fifo_16x16_tb ();    

sync_fifo_16x16 uut (
.clk      , // Clock input
.rst      , // Active high reset
.wr_cs    , // Write chip select
.rd_cs    , // Read chipe select
.data_in  , // Data input
.rd_en    , // Read enable
.wr_en    , // Write Enable
.data_out , // Data Output
.empty    , // FIFO empty
.full ,      // FIFO full
.address_to_write,
.address_to_read
);    

// FIFO constants
parameter DATA_WIDTH = 16;
parameter ADDR_WIDTH = 4;
parameter RAM_DEPTH = 16;

 
// FIFO constants
// Port Declarations
reg  clk ;
reg  rst ;
reg  wr_cs ;
reg  rd_cs ;
reg  rd_en ;
reg  wr_en ;
reg  [DATA_WIDTH-1:0] data_in ;
wire  full ;
wire  empty ;
wire  [DATA_WIDTH-1:0] data_out ;

reg  [ADDR_WIDTH-1:0] address_to_write ;
reg  [ADDR_WIDTH-1:0] address_to_read;
//-----------Internal variables-------------------



    always  begin
    #5 clk = !clk;  
	 end



    initial begin


	#5 rst = 1;  clk = 0 ;
	#5 rst = 0; 
	#5 rst = 1; 


	wr_cs = 1; 
	wr_en = 1; 
	rd_cs = 0; 
	rd_en = 0; 


        //$monitor(clk,b,c,d,out);
        for (int i=0; i<17; i=i+1) begin
            address_to_write = i ; 
	    data_in = i + 1;
            #10; 

		


        end 

	wr_cs = 0; 
	wr_en = 0; 
	rd_cs = 1; 
	rd_en = 1; 




        //$monitor(clk,b,c,d,out);
        for (int i=0; i<17; i=i+1) begin
            address_to_read = i ; 
            #10; 

        end 

	wr_cs = 0; 
	wr_en = 0; 
	rd_cs = 0; 
	rd_en = 0; 




  #600 $finish; 


    end




initial  begin
    $dumpfile ("sync_fifo_16x16_tb.vcd"); 
    $dumpvars; 
  end 



endmodule

RTLs_1409/sync_fifo_16x16_tb.vcd
$date
	Thu Sep 29 10:50:33 2022
$end
$version
	Icarus Verilog
$end
$timescale
	1ps
$end
$scope module sync_fifo_16x16_tb $end
$var wire 1 ! full $end
$var wire 1 " empty $end
$var wire 16 # data_out [15:0] $end
$var reg 4 $ address_to_read [3:0] $end
$var reg 4 % address_to_write [3:0] $end
$var reg 1 & clk $end
$var reg 16 ' data_in [15:0] $end
$var reg 1 ( rd_cs $end
$var reg 1 ) rd_en $end
$var reg 1 * rst $end
$var reg 1 + wr_cs $end
$var reg 1 , wr_en $end
$scope module uut $end
$var wire 4 - address_to_read [3:0] $end
$var wire 4 . address_to_write [3:0] $end
$var wire 1 & clk $end
$var wire 16 / data_in [15:0] $end
$var wire 1 ( rd_cs $end
$var wire 1 ) rd_en $end
$var wire 1 * rst $end
$var wire 1 + wr_cs $end
$var wire 1 , wr_en $end
$var wire 1 ! full $end
$var wire 1 " empty $end
$var wire 16 0 data_ram [15:0] $end
$var reg 16 1 data_out [15:0] $end
$var reg 4 2 rd_pointer [3:0] $end
$var reg 5 3 status_cnt [4:0] $end
$var reg 4 4 wr_pointer [3:0] $end
$scope module DP_RAM_IM $end
$var wire 4 5 address_0 [3:0] $end
$var wire 4 6 address_1 [3:0] $end
$var wire 1 + cs_0 $end
$var wire 1 ( cs_1 $end
$var wire 16 7 data_0 [15:0] $end
$var wire 1 8 oe_0 $end
$var wire 1 ) oe_1 $end
$var wire 1 , we_0 $end
$var wire 1 9 we_1 $end
$var wire 16 : data_1 [15:0] $end
$var reg 16 ; data_0_out [15:0] $end
$var reg 16 < data_1_out [15:0] $end
$scope begin MEM_READ_0 $end
$upscope $end
$scope begin MEM_READ_1 $end
$upscope $end
$scope begin MEM_WRITE $end
$upscope $end
$upscope $end
$scope begin READ_DATA $end
$upscope $end
$scope begin READ_POINTER $end
$upscope $end
$scope begin STATUS_COUNTER $end
$upscope $end
$scope begin WRITE_POINTER $end
$upscope $end
$upscope $end
$scope begin $ivl_for_loop0 $end
$var integer 32 = i [31:0] $end
$upscope $end
$scope begin $ivl_for_loop1 $end
$var integer 32 > i [31:0] $end
$upscope $end
$upscope $end
$enddefinitions $end
#0
$dumpvars
b0 >
b0 =
b0 <
b0 ;
b0xxxxxxxx :
09
08
bx 7
bx 6
bx 5
bx 4
bx 3
bx 2
bx 1
b0xxxxxxxx 0
bx /
bx .
bx -
x,
x+
x*
x)
x(
bx '
x&
bx %
bx $
bx #
x"
x!
$end
#5000
0&
1*
#10000
0!
1"
b0 3
b0 #
b0 1
b0 2
b0 6
b0 4
b0 5
0*
1&
#15000
b0zzzzzzzz 0
b0zzzzzzzz :
b1 '
b1 /
b1 7
b0 %
b0 .
0)
0(
1,
1+
1*
0&
#20000
0"
b1 3
1&
#25000
0&
b10 '
b10 /
b10 7
b1 %
b1 .
b1 =
#30000
b10 3
b1 4
b1 5
1&
#35000
0&
b11 '
b11 /
b11 7
b10 %
b10 .
b10 =
#40000
b11 3
b10 4
b10 5
1&
#45000
0&
b100 '
b100 /
b100 7
b11 %
b11 .
b11 =
#50000
b100 3
b11 4
b11 5
1&
#55000
0&
b101 '
b101 /
b101 7
b100 %
b100 .
b100 =
#60000
b101 3
b100 4
b100 5
1&
#65000
0&
b110 '
b110 /
b110 7
b101 %
b101 .
b101 =
#70000
b110 3
b101 4
b101 5
1&
#75000
0&
b111 '
b111 /
b111 7
b110 %
b110 .
b110 =
#80000
b111 3
b110 4
b110 5
1&
#85000
0&
b1000 '
b1000 /
b1000 7
b111 %
b111 .
b111 =
#90000
b1000 3
b111 4
b111 5
1&
#95000
0&
b1001 '
b1001 /
b1001 7
b1000 %
b1000 .
b1000 =
#100000
b1001 3
b1000 4
b1000 5
1&
#105000
0&
b1010 '
b1010 /
b1010 7
b1001 %
b1001 .
b1001 =
#110000
b1010 3
b1001 4
b1001 5
1&
#115000
0&
b1011 '
b1011 /
b1011 7
b1010 %
b1010 .
b1010 =
#120000
b1011 3
b1010 4
b1010 5
1&
#125000
0&
b1100 '
b1100 /
b1100 7
b1011 %
b1011 .
b1011 =
#130000
b1100 3
b1011 4
b1011 5
1&
#135000
0&
b1101 '
b1101 /
b1101 7
b1100 %
b1100 .
b1100 =
#140000
b1101 3
b1100 4
b1100 5
1&
#145000
0&
b1110 '
b1110 /
b1110 7
b1101 %
b1101 .
b1101 =
#150000
b1110 3
b1101 4
b1101 5
1&
#155000
0&
b1111 '
b1111 /
b1111 7
b1110 %
b1110 .
b1110 =
#160000
1!
b1111 3
b1110 4
b1110 5
1&
#165000
0&
b10000 '
b10000 /
b10000 7
b1111 %
b1111 .
b1111 =
#170000
0!
b10000 3
b1111 4
b1111 5
1&
#175000
0&
b10001 '
b10001 /
b10001 7
b0 %
b0 .
b10000 =
#180000
b0 4
b0 5
1&
#185000
b10001 <
b10001 0
b10001 :
0&
b0 $
b0 -
1)
1(
0,
0+
b10001 =
#190000
1!
b1111 3
b10001 #
b10001 1
1&
#195000
0&
b1 $
b1 -
b1 >
#200000
b11 0
b11 :
b11 <
0!
b1110 3
b1 2
b1 6
1&
#205000
0&
b10 $
b10 -
b10 >
#210000
b100 0
b100 :
b100 <
b1101 3
b11 #
b11 1
b10 2
b10 6
1&
#215000
0&
b11 $
b11 -
b11 >
#220000
b101 0
b101 :
b101 <
b1100 3
b100 #
b100 1
b11 2
b11 6
1&
#225000
0&
b100 $
b100 -
b100 >
#230000
b110 0
b110 :
b110 <
b1011 3
b101 #
b101 1
b100 2
b100 6
1&
#235000
0&
b101 $
b101 -
b101 >
#240000
b111 0
b111 :
b111 <
b1010 3
b110 #
b110 1
b101 2
b101 6
1&
#245000
0&
b110 $
b110 -
b110 >
#250000
b1000 0
b1000 :
b1000 <
b1001 3
b111 #
b111 1
b110 2
b110 6
1&
#255000
0&
b111 $
b111 -
b111 >
#260000
b1001 0
b1001 :
b1001 <
b1000 3
b1000 #
b1000 1
b111 2
b111 6
1&
#265000
0&
b1000 $
b1000 -
b1000 >
#270000
b1010 0
b1010 :
b1010 <
b111 3
b1001 #
b1001 1
b1000 2
b1000 6
1&
#275000
0&
b1001 $
b1001 -
b1001 >
#280000
b1011 0
b1011 :
b1011 <
b110 3
b1010 #
b1010 1
b1001 2
b1001 6
1&
#285000
0&
b1010 $
b1010 -
b1010 >
#290000
b1100 0
b1100 :
b1100 <
b101 3
b1011 #
b1011 1
b1010 2
b1010 6
1&
#295000
0&
b1011 $
b1011 -
b1011 >
#300000
b1101 0
b1101 :
b1101 <
b100 3
b1100 #
b1100 1
b1011 2
b1011 6
1&
#305000
0&
b1100 $
b1100 -
b1100 >
#310000
b1110 0
b1110 :
b1110 <
b11 3
b1101 #
b1101 1
b1100 2
b1100 6
1&
#315000
0&
b1101 $
b1101 -
b1101 >
#320000
b1111 0
b1111 :
b1111 <
b10 3
b1110 #
b1110 1
b1101 2
b1101 6
1&
#325000
0&
b1110 $
b1110 -
b1110 >
#330000
b10000 0
b10000 :
b10000 <
b1 3
b1111 #
b1111 1
b1110 2
b1110 6
1&
#335000
0&
b1111 $
b1111 -
b1111 >
#340000
b10001 0
b10001 :
b10001 <
1"
b0 3
b10000 #
b10000 1
b1111 2
b1111 6
1&
#345000
0&
b0 $
b0 -
b10000 >
#350000
b10001 #
b10001 1
b0 2
b0 6
1&
#355000
b0 <
b0zzzzzzzz 0
b0zzzzzzzz :
0&
0)
0(
b10001 >
